gza/__init__.py
gza/__main__.py
gza/_version.py
gza/branch_naming.py
gza/cli.py
gza/config.py
gza/db.py
gza/git.py
gza/github.py
gza/importer.py
gza/runner.py
gza/tasks.py
gza/workers.py
gza/providers/__init__.py
gza/providers/base.py
gza/providers/claude.py
gza/providers/gemini.py
gza_agent-0.2.0.dist-info/METADATA
gza_agent-0.2.0.dist-info/WHEEL
gza_agent-0.2.0.dist-info/entry_points.txt
gza_agent-0.2.0.dist-info/licenses/LICENSE
gza_agent-0.2.0.dist-info/RECORD
