Metadata-Version: 2.4
Name: gza-agent
Version: 0.2.0
Summary: A coding AI agent runner for Claude Code
Project-URL: Homepage, https://github.com/mhawthorne/gza
Project-URL: Repository, https://github.com/mhawthorne/gza
Project-URL: Issues, https://github.com/mhawthorne/gza/issues
Author-email: Matthew Hawthorne <mh@supremeinformatics.com>
License-Expression: MIT
License-File: LICENSE
Keywords: agent,ai,automation,claude,cli,runner
Classifier: Development Status :: 3 - Alpha
Classifier: Environment :: Console
Classifier: Intended Audience :: Developers
Classifier: License :: OSI Approved :: MIT License
Classifier: Programming Language :: Python :: 3
Classifier: Programming Language :: Python :: 3.11
Classifier: Programming Language :: Python :: 3.12
Classifier: Programming Language :: Python :: 3.13
Classifier: Topic :: Software Development
Classifier: Typing :: Typed
Requires-Python: >=3.11
Requires-Dist: pyyaml>=6.0
Provides-Extra: dev
Requires-Dist: build>=1.0; extra == 'dev'
Requires-Dist: pre-commit>=3.0; extra == 'dev'
Requires-Dist: pytest>=8.0; extra == 'dev'
Requires-Dist: twine>=5.0; extra == 'dev'
